README.md
setup.py
deepDegron/__init__.py
deepDegron/deep_degron.py
deepDegron/degron_pred.py
deepDegron/motif_analysis.py
deepDegron/pvalue.py
deepDegron/run_saturation_mutagenesis.py
deepDegron/score_mutations.py
deepDegron/sequence_context.py
deepDegron/simulation.py
deepDegron/statistical_test.py
deepDegron/train_cterm_nn.py
deepDegron/train_nterm_nn.py
deepDegron/utils.py
deepDegron/variants.py
deepDegron.egg-info/PKG-INFO
deepDegron.egg-info/SOURCES.txt
deepDegron.egg-info/dependency_links.txt
deepDegron.egg-info/entry_points.txt
deepDegron.egg-info/requires.txt
deepDegron.egg-info/top_level.txt