Metadata-Version: 2.1
Name: deepDegron
Version: 1.1.0
Summary: deepDegron
Home-page: https://github.com/ctokheim/deepDegron
Author: Collin Tokheim
Author-email: fake@gmail.com
License: Apache License, Version 2.0
Platform: UNKNOWN
Classifier: Topic :: Scientific/Engineering :: Bio-Informatics
Classifier: Environment :: Console
Classifier: Intended Audience :: Developers
Classifier: Intended Audience :: Science/Research
